comfyui_nuvu-1.0.53.dist-info/WHEEL
comfyui_nuvu-1.0.53.dist-info/top_level.txt
comfyui_nuvu-1.0.53.dist-info/METADATA
comfyui_nuvu/pip_utils.so
comfyui_nuvu/uv_installer.so
comfyui_nuvu/nuvu_server.so
comfyui_nuvu/__init__.py
comfyui_nuvu/web/updater.so
comfyui_nuvu/web/workflow_downloader.so
comfyui_nuvu/web/model_downloads.so
comfyui_nuvu/web/package_installer.so
comfyui_nuvu/web/__init__.py
comfyui_nuvu/web/analytics.so
comfyui_nuvu/web/setup_modules/auth.so
comfyui_nuvu/web/setup_modules/downloads.so
comfyui_nuvu/web/setup_modules/environment.so
comfyui_nuvu/web/setup_modules/utils.so
comfyui_nuvu/web/setup_modules/logging_setup.so
comfyui_nuvu/web/setup_modules/custom_nodes.so
comfyui_nuvu/web/setup_modules/__init__.py
comfyui_nuvu/web/setup_modules/file_operations.so
comfyui_nuvu/web/setup_modules/config.so
comfyui_nuvu/web/installers/sageattention_installer.so
comfyui_nuvu/web/installers/onnxruntime_installer.so
comfyui_nuvu/web/installers/shared.so
comfyui_nuvu/web/installers/pytorch_installer.so
comfyui_nuvu/web/installers/cuda_installer.so
comfyui_nuvu/web/installers/__init__.py
comfyui_nuvu/web/installers/triton_installer.so
comfyui_nuvu/web/installers/vs_build_tools_installer.so
comfyui_nuvu-1.0.53.dist-info/RECORD
