Metadata-Version: 2.4
Name: comfyui-nuvu
Version: 1.0.53
Summary: www.nuvulabs.ai | Install missing models & custom nodes, production ready VFX & film subgraphs and workflows for secure offline generation, and dependency installations including SageAttention and Triton.
Author: Nuvu Labs
License: Proprietary
Project-URL: Homepage, https://github.com/nuvulabs/ComfyUI-Nuvu
Project-URL: Repository, https://github.com/nuvulabs/ComfyUI-Nuvu
Classifier: Development Status :: 4 - Beta
Classifier: Intended Audience :: Developers
Classifier: Operating System :: OS Independent
Classifier: Programming Language :: Python :: 3
Classifier: Programming Language :: Python :: 3.9
Classifier: Programming Language :: Python :: 3.10
Classifier: Programming Language :: Python :: 3.11
Classifier: Programming Language :: Python :: 3.12
Requires-Python: >=3.9
Requires-Dist: requests>=2.31.0
Requires-Dist: huggingface_hub[hf_transfer]<1.0,>=0.34.0
Requires-Dist: hf_xet
Requires-Dist: keyring>=24.3.0
Dynamic: requires-python
